MANIFEST.in
README.md
requirements.txt
setup.py
translator/__init__.py
translator/client.py
translator/data.py