Metadata-Version: 1.0
Name: gtt-python-client
Version: 0.1
Summary: Python bindings for Google Translator Toolkit API.
Home-page: https://github.com/jellycrystal/gtt-python-client
Author: Yury Yurevich
Author-email: yyurevich@jellycrystal.com
License: BSD
Platform: UNKNOWN
Classifier: Development Status :: 3 - Alpha
Classifier: Intended Audience :: Developers
Classifier: License :: OSI Approved :: BSD License
Classifier: Operating System :: OS Independent
Classifier: Programming Language :: Python
Classifier: Topic :: Software Development :: Libraries :: Python Modules
